setup.py
frasco_countries/__init__.py
frasco_countries/db.py
frasco_countries/form.py
frasco_countries.egg-info/PKG-INFO
frasco_countries.egg-info/SOURCES.txt
frasco_countries.egg-info/dependency_links.txt
frasco_countries.egg-info/not-zip-safe
frasco_countries.egg-info/requires.txt
frasco_countries.egg-info/top_level.txt