Metadata-Version: 1.0
Name: frasco-countries
Version: 0.1
Summary: pycountry integration for Frasco
Home-page: http://github.com/frascoweb/frasco-countries
Author: Maxime Bouroumeau-Fuseau
Author-email: maxime.bouroumeau@gmail.com
License: MIT
Platform: any
